multi_choices_parser-0.10.0.dist-info/WHEEL
multi_choices_parser-0.10.0.dist-info/METADATA
multi_choices_parser-0.10.0.dist-info/RECORD
multi_choices_parser-0.10.0.dist-info/licenses/LICENSE
multi_choices_parser/__init__.py
multi_choices_parser/_core.pyi
multi_choices_parser/_core.cpython-310-x86_64-linux-gnu.so
multi_choices_parser/parser.py
