Metadata-Version: 2.1
Name: multi-choices-parser
Version: 0.10.0
Summary: An efficient C++ incremental parser for multi-choices grammars (generalization of the trie structure) with Python bindings.
Author-Email: Hichem Ammar Khodja <hichem5696@gmail.com>
Project-URL: Homepage, https://github.com/HichemAK/multi-choices-parser
Requires-Python: >=3.8
